sapphyre_tools-0.9.2.dist-info/METADATA
sapphyre_tools-0.9.2.dist-info/WHEEL
sapphyre_tools-0.9.2.dist-info/licenses/LICENSE
sapphyre_tools/__init__.py
sapphyre_tools/sapphyre_tools.cpython-312-x86_64-linux-gnu.so
sapphyre_tools-0.9.2.dist-info/RECORD
