Metadata-Version: 2.4
Name: sapphyre_tools
Version: 0.9.2
Classifier: Development Status :: 4 - Beta
Classifier: Intended Audience :: Developers
Classifier: Programming Language :: Rust
Classifier: Programming Language :: Python :: 3.8
Classifier: Programming Language :: Python :: 3.9
Classifier: Programming Language :: Python :: 3.10
Classifier: Programming Language :: Python :: 3.11
Classifier: Programming Language :: Python :: 3.12
Classifier: Programming Language :: Python :: 3.13
Classifier: Programming Language :: Python :: Implementation :: CPython
Classifier: Topic :: Software Development :: Libraries
License-File: LICENSE
Keywords: Python wrapper,high-performance
Author: Michael Valentine
Author-email: mvalentine65@gmail.com
License: Apache-2.0
Requires-Python: >=3.8
